{"total":2715,"count":20,"hits":[{"_id":"2506","sc":"喻","tc":null,"pinyin":"yù","definition":"喻\n\n[yù] 比喻 bǐyù analogy; 隐喻 yǐnyù metaphor"},{"_id":"2510","definition":"框\n\n[kuàng] frame; case; circle","sc":"框","pinyin":"kuàng"},{"_id":"2511","definition":"缴 (F 繳)\n\n[jiǎo] hand in, pay\n\n[zhuó] silk string attached to an arrow for shooting birds","sc":"缴","tc":"繳","pinyin":"jiǎo"},{"_id":"2512","definition":"蹈\n\n[dǎo] skip; step; 舞蹈 wǔdǎo dance","sc":"蹈","pinyin":"dǎo"},{"_id":"2513","definition":"哨\n\n[shào] whistle; chirp; sentry post","sc":"哨","pinyin":"shào"},{"_id":"2515","definition":"颖 (F 穎)\n\n[yǐng] 新颖 xīnyǐng new and original, novel","sc":"颖","tc":"穎","pinyin":"yǐng"},{"_id":"2516","definition":"菊\n\n[jú] chrysanthemum","sc":"菊","pinyin":"jú"},{"_id":"2518","definition":"喀\n\n[kā] (sound of coughing or vomiting)","sc":"喀","pinyin":"kā"},{"_id":"2519","definition":"妆 (F 妝)\n\n[zhuāng] adorn oneself; 妆奁 bride's trousseau","sc":"妆","tc":"妝","pinyin":"zhuāng"},{"_id":"2520","definition":"淹\n\n[yān] flood; 淹死 drown","sc":"淹","pinyin":"yān"},{"_id":"2521","definition":"瓷\n\n[cí] porcelain, china; 陶瓷 táocí ceramics","sc":"瓷","pinyin":"cí"},{"_id":"2523","definition":"淀\n\n[diàn] shallow water; (F 澱) form sediment; settle; precipitate; 淀粉 diànfěn starch","sc":"淀","pinyin":"diàn"},{"_id":"2524","definition":"蜡 (F 蠟)\n\n[là] wax, polish, yellowish, (=蜡烛 làzhú) candle","sc":"蜡","tc":"蠟","pinyin":"là"},{"_id":"2525","definition":"嚼\n\n[jué] 咀嚼 jǔjué chew\n\n[jiáo] chew\n\n[jiào] 倒嚼","sc":"嚼","pinyin":"jué"},{"_id":"2526","definition":"剂 (F 劑)\n\n[jì] dose","sc":"剂","tc":"劑","pinyin":"jì"},{"_id":"2527","definition":"逛\n\n[guàng] stroll, ramble, roam","sc":"逛","pinyin":"guàng"},{"_id":"2529","definition":"骤 (F 驟)\n\n[zhòu] gallop; 步骤 bùzhòu procedure; 骤然 zhòurán suddenly","sc":"骤","tc":"驟","pinyin":"zhòu"},{"_id":"2530","definition":"暑\n\n[shǔ] hot weather; 暑假 (shǔjià) summer vacation","sc":"暑","pinyin":"shǔ"},{"_id":"2531","definition":"襟\n\n[jīn] front of garment, bros. in law; 衣襟 yījīn front of Chinese jacket","sc":"襟","pinyin":"jīn"},{"_id":"2534","definition":"庐 (F 廬)\n\n[lú] hut, cottage","sc":"庐","tc":"廬","pinyin":"lú"}]}