{"total":2715,"count":20,"hits":[{"_id":"641","sc":"买","tc":"買","pinyin":"mǎi","definition":"买 (F 買)\n\n[mǎi] buy"},{"_id":"642","definition":"户 (F 戶)\n\n[hù] door, household; 窗户 chuānghù window","sc":"户","tc":"戶","pinyin":"hù"},{"_id":"643","definition":"护 (F 護)\n\n[hù] (= 保护 bǎohù) guard, protect; 护士 hùshi nurse","sc":"护","tc":"護","pinyin":"hù"},{"_id":"644","definition":"喝\n\n[hē] drink\n\n[hè] shout","sc":"喝","pinyin":"hē"},{"_id":"645","definition":"朋\n\n[péng] 朋友 péngyǒu friend\n\n{Compare with 丽 lì beautiul and 册 cè book}","sc":"朋","pinyin":"péng"},{"_id":"646","definition":"供\n\n[gōng] supply\n\n[gòng] confess","sc":"供","pinyin":"gōng"},{"_id":"647","definition":"责 (F 責)\n\n[zé] duty; 责任 zérèn responsibility","sc":"责","tc":"責","pinyin":"zé"},{"_id":"648","definition":"项 (F 項)\n\n[xiàng] (= 项目 xiàngmù) item","sc":"项","tc":"項","pinyin":"xiàng"},{"_id":"649","definition":"背\n\n[bèi] back\n\n[bēi] carry on the back","sc":"背","pinyin":"bèi"},{"_id":"650","definition":"余\n\n[yú] I, me, (F 餘) left-over, extra; 其余 the rest; 余弦 cosine","sc":"余","pinyin":"yú"},{"_id":"651","definition":"希\n\n[xī] sparse, scattered, watery, this;\n\n    希望 xīwàng hope;\n\n    希奇 xīqí rare, strange;\n\n    希腊 Xīlà Greece","sc":"希","pinyin":"xī"},{"_id":"652","definition":"卫 (F 衛)\n\n[wèi] 保卫 defend; 卫生 sanitary; 卫星 satellite","sc":"卫","tc":"衛","pinyin":"wèi"},{"_id":"653","definition":"列\n\n[liè] column, line up; 列车 lièchē train; 排列 páiliè arrange","sc":"列","pinyin":"liè"},{"_id":"654","definition":"图 (F 圖)\n\n[tú] picture; 地图 dìtú map; 图书馆 túshūguǎn library","sc":"图","tc":"圖","pinyin":"tú"},{"_id":"655","definition":"室\n\n[shì] room; 教室 jiàoshì classroom; 卧室 wòshì bedroom; 办公室 bàngōngshì office","sc":"室","pinyin":"shì"},{"_id":"656","definition":"乱 (F 亂)\n\n[luàn] chaotic, disorderly, messy; 混乱 hùnluàn chaos","sc":"乱","tc":"亂","pinyin":"luàn"},{"_id":"657","definition":"刘 (F 劉)\n\n[Liú] <family name>","sc":"刘","tc":"劉","pinyin":"Liú"},{"_id":"658","definition":"爷 (F 爺)\n\n[yé] father; 爷爷 yéye grandpa","sc":"爷","tc":"爺","pinyin":"yé"},{"_id":"659","definition":"龙 (F 龍)\n\n[lóng] dragon; 恐龙 kǒnglóng dinosaur","sc":"龙","tc":"龍","pinyin":"lóng"},{"_id":"660","definition":"咱\n\n[zán] (= 咱们 zánmen) we = you and I\n\n[zan] (abbreviation for 早晚 zǎowǎn) all the time, morning and evening, sooner or later","sc":"咱","pinyin":"zán"}]}