{"total":2715,"count":20,"hits":[{"_id":"1201","sc":"届","tc":"屆","pinyin":"jiè","definition":"届 (F 屆)\n\n[jiè] to fall due, <classifier for year of graduation, regular sessions, meetings, etc.>"},{"_id":"1202","definition":"迹 (F 跡)\n\n[jì] (=痕迹 hénjì) mark, trace, vestige; 奇迹 qíjì miracle","sc":"迹","tc":"跡","pinyin":"jì"},{"_id":"1203","definition":"雷\n\n[léi] thunder; 雷雨 thunderstorm; 雷达 radar","sc":"雷","pinyin":"léi"},{"_id":"1204","definition":"序\n\n[xù] 秩序 zhìxu order; 程序 procedure; 次序 order","sc":"序","pinyin":"xù"},{"_id":"1205","definition":"寒\n\n[hán] (寒冷) cold","sc":"寒","pinyin":"hán"},{"_id":"1206","definition":"附\n\n[fù] enclose, attach; 附近 fùjìn vicinity, nearby","sc":"附","pinyin":"fù"},{"_id":"1207","definition":"鸡 (F 雞)\n\n[jī] chicken; 宫保鸡丁 gōngbǎo jīdīng spicy diced chicken","sc":"鸡","tc":"雞","pinyin":"jī"},{"_id":"1208","definition":"遭\n\n[zāo] meet with disaster","sc":"遭","pinyin":"zāo"},{"_id":"1209","definition":"挑\n\n[tiāo] (挑选) choose\n\n[tiǎo] poke; 挑战 challenge\n\n[tāo] 挑达 tāotà walk casually to and fro","sc":"挑","pinyin":"tiāo"},{"_id":"1210","definition":"肩\n\n[jiān] (肩膀 jiānbǎng) shoulder; (肩负 jiānfù) take on","sc":"肩","pinyin":"jiān"},{"_id":"1211","definition":"忆 (F 憶)\n\n[yì] (记忆 jìyì, 回忆 huíyì) remember, recall; memory","sc":"忆","tc":"憶","pinyin":"yì"},{"_id":"1212","definition":"柔\n\n[róu] yielding; 柔软 róuruǎn soft; 柔和 róuhe gentle","sc":"柔","pinyin":"róu"},{"_id":"1213","definition":"戴\n\n[dài] put on;\n\n    戴眼镜 dài yǎnjìng wear glasses;\n\n    戴上帽子 dàishang màozi put on a hat","sc":"戴","pinyin":"dài"},{"_id":"1214","definition":"惜\n\n[xī] (珍惜) cherish; 可惜 kěxī it's too bad; 不惜 bùxī not hesitate","sc":"惜","pinyin":"xī"},{"_id":"1215","definition":"隔\n\n[gé] separate, stand between; 隔壁 next door","sc":"隔","pinyin":"gé"},{"_id":"1216","definition":"豪\n\n[háo] (=毫不 hǎobù, =好不 hǎobù) not at all","sc":"豪","pinyin":"háo"},{"_id":"1217","definition":"诚 (F 誠)\n\n[chéng] (诚实) honest","sc":"诚","tc":"誠","pinyin":"chéng"},{"_id":"1218","definition":"瑞\n\n[ruì] auspicious, good omen; 瑞雪 timely snow","sc":"瑞","pinyin":"ruì"},{"_id":"1219","definition":"减 (F 減)\n\n[jiǎn] subtract; 减少 jiǎnshǎo decrease","sc":"减","tc":"減","pinyin":"jiǎn"},{"_id":"1220","definition":"播\n\n[bō] sow, seed; 广播 broadcast; 传播 disseminate","sc":"播","pinyin":"bō"}]}