{"total":2715,"count":20,"hits":[{"_id":"1441","sc":"霞","tc":null,"pinyin":"xiá","definition":"霞\n\n[xiá] rosy clouds"},{"_id":"1442","definition":"猪 (F 豬)\n\n[zhū] pig; 猪年 zhūnián the year of the pig = the 12th year","sc":"猪","tc":"豬","pinyin":"zhū"},{"_id":"1443","definition":"悉\n\n[xī] 熟悉 shúxī know well, be familiar with","sc":"悉","pinyin":"xī"},{"_id":"1444","definition":"扎\n\n[zhā] prick\n\n[zhá] 挣扎 zhēngzhá struggle\n\n[zā] 包扎","sc":"扎","pinyin":"zhā"},{"_id":"1445","definition":"劝 (F 勸)\n\n[quàn] advise","sc":"劝","tc":"勸","pinyin":"quàn"},{"_id":"1446","definition":"薄\n\n[báo] thin\n\n[bó] slight; 薄弱 weak\n\n[bò] 薄荷 bòhe peppermint","sc":"薄","pinyin":"báo"},{"_id":"1447","definition":"筑 (F 築)\n\n[zhù] build, construct; 建筑学 architecture","sc":"筑","tc":"築","pinyin":"zhù"},{"_id":"1448","definition":"俊\n\n[jùn] handsome, pretty; 英俊 brilliant, talented","sc":"俊","pinyin":"jùn"},{"_id":"1449","definition":"鞋\n\n[xié] shoe","sc":"鞋","pinyin":"xié"},{"_id":"1450","definition":"距\n\n[jù] (距离 jùlí) distance","sc":"距","pinyin":"jù"},{"_id":"1451","definition":"侵\n\n[qīn] (= 侵略 qīnlüè, = 侵入 qīnrù) invade, intrude into","sc":"侵","pinyin":"qīn"},{"_id":"1452","definition":"欣\n\n[xīn] 欣赏 xīnshǎng enjoy","sc":"欣","pinyin":"xīn"},{"_id":"1453","definition":"挤 (F 擠)\n\n[jǐ] squeeze; crowd; push, jostle; 拥挤 yōngjǐ crowded","sc":"挤","tc":"擠","pinyin":"jǐ"},{"_id":"1454","definition":"媒\n\n[méi] go-between, matchmaker; 媒介 medium, intermediary","sc":"媒","pinyin":"méi"},{"_id":"1455","definition":"吐\n\n[tǔ] spit\n\n[tù] (呕吐 ǒutù) vomit","sc":"吐","pinyin":"tǔ"},{"_id":"1456","definition":"魂\n\n[hún] (灵魂 línghún) soul, spirit, mood","sc":"魂","pinyin":"hún"},{"_id":"1457","definition":"洁 (F 潔)\n\n[jié] (= 纯洁 chúnjié) pure, (= 清洁 qīngjié) clean, sanitay;\n\n洁白 jiébái pure white, spotless","sc":"洁","tc":"潔","pinyin":"jié"},{"_id":"1458","definition":"枝\n\n[zhī] branch\n\n[qí] (= 歧 qí) fork, brach, divergent","sc":"枝","pinyin":"zhī"},{"_id":"1459","definition":"盈\n\n[yíng] full; 盈利 yínglì profit, have a surplus","sc":"盈","pinyin":"yíng"},{"_id":"1460","definition":"阻\n\n[zǔ] block; 阻止 zǔzhǐ prevent; 电阻 diànzǔ resistance","sc":"阻","pinyin":"zǔ"}]}